an_quickviper3/__init__.py
an_quickviper3/quickviper3.py
an_quickviper3-1.4.0.dist-info/licenses/LICENSE
an_quickviper3-1.4.0.dist-info/METADATA
an_quickviper3-1.4.0.dist-info/WHEEL
an_quickviper3-1.4.0.dist-info/top_level.txt
an_quickviper3-1.4.0.dist-info/RECORD
