Metadata-Version: 2.4
Name: an_quickviper3
Version: 1.4.0
Summary: A package for an_quickviper3.
Home-page: https://github.com/Atsushi888/Atsushi888
Author: Atsushi888
Author-email: Atsushi888 <vtgrotxu@gmail.com>
Project-URL: Homepage, https://github.com/Atsushi888/an_quickviper3
Project-URL: Repository, https://github.com/Atsushi888/an_quickviper3
Requires-Python: >=3.6
License-File: LICENSE
Requires-Dist: an_DebugHelper>=1.3.3
Requires-Dist: an_UniqueEnvVar>=0.1.5
Requires-Dist: an_ToolKit
Requires-Dist: an_EasyVen
Dynamic: author
Dynamic: home-page
Dynamic: license-file
Dynamic: requires-python
